odoo8_addon_stock_available_sale-8.0.3.0.0.99.dev24-py3.8-nspkg.pth
odoo_addons/stock_available_sale/README.rst
odoo_addons/stock_available_sale/__init__.py
odoo_addons/stock_available_sale/__openerp__.py
odoo_addons/stock_available_sale/i18n/ca.po
odoo_addons/stock_available_sale/i18n/de.po
odoo_addons/stock_available_sale/i18n/el_GR.po
odoo_addons/stock_available_sale/i18n/es.po
odoo_addons/stock_available_sale/i18n/es_ES.po
odoo_addons/stock_available_sale/i18n/es_MX.po
odoo_addons/stock_available_sale/i18n/fi.po
odoo_addons/stock_available_sale/i18n/fr.po
odoo_addons/stock_available_sale/i18n/fr_CH.po
odoo_addons/stock_available_sale/i18n/fr_FR.po
odoo_addons/stock_available_sale/i18n/gl.po
odoo_addons/stock_available_sale/i18n/hr.po
odoo_addons/stock_available_sale/i18n/hr_HR.po
odoo_addons/stock_available_sale/i18n/it.po
odoo_addons/stock_available_sale/i18n/nl.po
odoo_addons/stock_available_sale/i18n/nl_NL.po
odoo_addons/stock_available_sale/i18n/pt.po
odoo_addons/stock_available_sale/i18n/pt_BR.po
odoo_addons/stock_available_sale/i18n/ro.po
odoo_addons/stock_available_sale/i18n/ru.po
odoo_addons/stock_available_sale/i18n/sk.po
odoo_addons/stock_available_sale/i18n/sl.po
odoo_addons/stock_available_sale/i18n/stock_available_sale.pot
odoo_addons/stock_available_sale/i18n/tr.po
odoo_addons/stock_available_sale/i18n/tr_TR.po
odoo_addons/stock_available_sale/i18n/vi_VN.po
odoo_addons/stock_available_sale/i18n/zh_CN.po
odoo_addons/stock_available_sale/models/__init__.py
odoo_addons/stock_available_sale/models/product_product.py
odoo_addons/stock_available_sale/models/product_template.py
odoo_addons/stock_available_sale/static/description/icon.png
odoo_addons/stock_available_sale/tests/__init__.py
odoo_addons/stock_available_sale/tests/test_quoted_qty.py
odoo_addons/stock_available_sale/views/product_template_view.xml
odoo8_addon_stock_available_sale-8.0.3.0.0.99.dev24.dist-info/METADATA
odoo8_addon_stock_available_sale-8.0.3.0.0.99.dev24.dist-info/WHEEL
odoo8_addon_stock_available_sale-8.0.3.0.0.99.dev24.dist-info/namespace_packages.txt
odoo8_addon_stock_available_sale-8.0.3.0.0.99.dev24.dist-info/top_level.txt
odoo8_addon_stock_available_sale-8.0.3.0.0.99.dev24.dist-info/RECORD
