Metadata-Version: 2.1
Name: odoo8-addon-stock-available-sale
Version: 8.0.3.0.0.99.dev24
Summary: Quotations in quantity available to promise
Home-page: UNKNOWN
Author: Numérigraphe,Odoo Community Association (OCA)
Author-email: support@odoo-community.org
License: AGPL-3
Platform: UNKNOWN
Classifier: Programming Language :: Python
Classifier: Framework :: Odoo
Classifier: Framework :: Odoo :: 8.0
Classifier: License :: OSI Approved :: GNU Affero General Public License v3
Requires-Python: ~=2.7
Requires-Dist: odoo8-addon-stock-available
Requires-Dist: odoo (<9.0a,>=8.0a)
